pd_helper/__init__.py
pd_helper/helper.py
pd_helper/maker.py
pd_helper/tests/__init__.py
pd_helper/tests/test__config.py
pd_helper/tests/test__mem_usage.py
pd_helper/tests/test__parse_cols.py
pd_helper/tests/test__reduce_precision.py
pd_helper/tests/test_maker.py
pd_helper/utils/__init__.py
pd_helper/utils/_configuration.py
pd_helper/utils/_mem_usage.py
pd_helper/utils/_parse_cols.py
pd_helper/utils/_reduce_precision.py
pd_helper-1.0.0.dist-info/METADATA
pd_helper-1.0.0.dist-info/WHEEL
pd_helper-1.0.0.dist-info/top_level.txt
pd_helper-1.0.0.dist-info/RECORD
