Metadata-Version: 2.1
Name: pd-helper
Version: 1.0.0
Summary: A helpful script to optimize a Pandas DataFrame.
Home-page: https://github.com/justinhchae/pd-helper
Author: Justin Chae
Author-email: justin@chaemail.com
License: UNKNOWN
Project-URL: Download URL, https://github.com/justinhchae/pd-helper/archive/refs/tags/v1.0.0.tar.gz
Platform: UNKNOWN
Classifier: Development Status :: 5 - Production/Stable
Classifier: Programming Language :: Python :: 3
Classifier: License :: OSI Approved :: MIT License
Classifier: Operating System :: OS Independent
Classifier: Intended Audience :: Developers
Classifier: Topic :: Software Development :: Build Tools
Requires-Python: >=3.8
Requires-Dist: pandas
Requires-Dist: numpy
Requires-Dist: tqdm
Requires-Dist: shortuuid
